_algopy_testing/__init__.py
_algopy_testing/arc4.py
_algopy_testing/compiled.py
_algopy_testing/constants.py
_algopy_testing/context.py
_algopy_testing/enums.py
_algopy_testing/gtxn.py
_algopy_testing/itxn.py
_algopy_testing/itxn_loader.py
_algopy_testing/mutable.py
_algopy_testing/protocols.py
_algopy_testing/py.typed
_algopy_testing/serialize.py
_algopy_testing/utils.py
_algopy_testing/context_helpers/__init__.py
_algopy_testing/context_helpers/context_storage.py
_algopy_testing/context_helpers/ledger_context.py
_algopy_testing/context_helpers/txn_context.py
_algopy_testing/decorators/__init__.py
_algopy_testing/decorators/arc4.py
_algopy_testing/decorators/subroutine.py
_algopy_testing/models/__init__.py
_algopy_testing/models/account.py
_algopy_testing/models/application.py
_algopy_testing/models/asset.py
_algopy_testing/models/contract.py
_algopy_testing/models/logicsig.py
_algopy_testing/models/template_variable.py
_algopy_testing/models/txn_fields.py
_algopy_testing/models/unsigned_builtins.py
_algopy_testing/op/__init__.py
_algopy_testing/op/block.py
_algopy_testing/op/constants.py
_algopy_testing/op/crypto.py
_algopy_testing/op/global_values.py
_algopy_testing/op/itxn.py
_algopy_testing/op/misc.py
_algopy_testing/op/pure.py
_algopy_testing/op/txn.py
_algopy_testing/primitives/__init__.py
_algopy_testing/primitives/array.py
_algopy_testing/primitives/biguint.py
_algopy_testing/primitives/bytes.py
_algopy_testing/primitives/string.py
_algopy_testing/primitives/uint64.py
_algopy_testing/state/__init__.py
_algopy_testing/state/box.py
_algopy_testing/state/global_state.py
_algopy_testing/state/local_state.py
_algopy_testing/state/utils.py
_algopy_testing/utilities/__init__.py
_algopy_testing/utilities/budget.py
_algopy_testing/utilities/log.py
_algopy_testing/utilities/size_of.py
_algopy_testing/value_generators/__init__.py
_algopy_testing/value_generators/arc4.py
_algopy_testing/value_generators/avm.py
_algopy_testing/value_generators/txn.py
algopy/__init__.py
algorand_python_testing-1.1.0.dist-info/METADATA
algorand_python_testing-1.1.0.dist-info/WHEEL
algorand_python_testing-1.1.0.dist-info/licenses/LICENSE
algorand_python_testing-1.1.0.dist-info/RECORD
